RuG_IntroToOptimization/ImageTools.py
RuG_IntroToOptimization/__init__.py
RuG_IntroToOptimization/blurring_operator.py
RuG_IntroToOptimization/discrete_gradient.py
rug_introtooptimization-0.0.9.dist-info/licenses/LICENSE
rug_introtooptimization-0.0.9.dist-info/METADATA
rug_introtooptimization-0.0.9.dist-info/WHEEL
rug_introtooptimization-0.0.9.dist-info/top_level.txt
rug_introtooptimization-0.0.9.dist-info/RECORD
