Metadata-Version: 2.4
Name: RuG_IntroToOptimization
Version: 0.0.9
Summary: A small package to help students implement the computational exercises in the RuG course 'Introduction to Optimization'.
Author-email: Daniel Cortild <d.cortild@rug.nl>
Project-URL: Homepage, https://github.com/DanielCortild/IntroductionToOptimization
Project-URL: Issues, https://github.com/DanielCortild/IntroductionToOptimization/issues
Classifier: Programming Language :: Python :: 3
Classifier: License :: OSI Approved :: MIT License
Classifier: Operating System :: OS Independent
Requires-Python: >=3.8
License-File: LICENSE
Requires-Dist: numpy
Requires-Dist: scipy
Requires-Dist: Pillow
Requires-Dist: matplotlib
Dynamic: license-file
